MANIFEST.in
README.rst
requirements.txt
setup.py
Marguerite.egg-info/PKG-INFO
Marguerite.egg-info/SOURCES.txt
Marguerite.egg-info/dependency_links.txt
Marguerite.egg-info/requires.txt
Marguerite.egg-info/top_level.txt
example/__init__.py
example/main.py
example/user.py
marguerite/__init__.py
marguerite/app.py
marguerite/utils.py
marguerite/accessors/__init__.py
marguerite/accessors/abstract.py
marguerite/accessors/bind.py
marguerite/accessors/sql.py
marguerite/structures/__init__.py
marguerite/structures/abstract.py
marguerite/structures/order.py
marguerite/structures/sql.py
tests/__init__.py
tests/sql/__init__.py
tests/sql/structure.py
tests/sql/test_sqlalchemy.py