Metadata-Version: 1.1
Name: Marguerite
Version: 1.0.2
Summary: Marguerite provides a declarative, consistent accessor to data layer.
Home-page: https://github.com/teitei-tk/Marguerite
Author: teitei-tk
Author-email: teitei.tk@gmail.com
License: MIT
Download-URL: https://github.com/teitei-tk/Marguerite/archive/master.tar.gz
Keywords: Marguerite,dispatcher,architecture,SQLAlchemy
Platform: UNKNOWN
Classifier: Development Status :: 5 - Production/Stable
Classifier: License :: OSI Approved :: Apache Software License
Classifier: Programming Language :: Python :: 2.7
Classifier: Programming Language :: Python :: 3
Classifier: Topic :: Software Development
Classifier: Topic :: Software Development :: Libraries
